MANIFEST.in
README.rst
setup.py
docs/HISTORY.txt
docs/LICENSE.GPL
docs/LICENSE.txt
ftw/__init__.py
ftw.faqblock.egg-info/PKG-INFO
ftw.faqblock.egg-info/SOURCES.txt
ftw.faqblock.egg-info/dependency_links.txt
ftw.faqblock.egg-info/entry_points.txt
ftw.faqblock.egg-info/namespace_packages.txt
ftw.faqblock.egg-info/not-zip-safe
ftw.faqblock.egg-info/requires.txt
ftw.faqblock.egg-info/top_level.txt
ftw/faqblock/__init__.py
ftw/faqblock/configure.zcml
ftw/faqblock/interfaces.py
ftw/faqblock/lawgiver.zcml
ftw/faqblock/permissions.zcml
ftw/faqblock/resources.zcml
ftw/faqblock/testing.py
ftw/faqblock/Extensions/__init__.py
ftw/faqblock/Extensions/install.py
ftw/faqblock/browser/__init__.py
ftw/faqblock/browser/configure.zcml
ftw/faqblock/browser/faqblock.pt
ftw/faqblock/browser/faqblock.py
ftw/faqblock/contents/__init__.py
ftw/faqblock/contents/configure.zcml
ftw/faqblock/contents/faqblock.py
ftw/faqblock/contents/interfaces.py
ftw/faqblock/locales/ftw.faqblock.pot
ftw/faqblock/locales/de/LC_MESSAGES/ftw.faqblock.po
ftw/faqblock/locales/en/LC_MESSAGES/ftw.faqblock.po
ftw/faqblock/profiles/default/browserlayer.xml
ftw/faqblock/profiles/default/jsregistry.xml
ftw/faqblock/profiles/default/metadata.xml
ftw/faqblock/profiles/default/propertiestool.xml
ftw/faqblock/profiles/default/rolemap.xml
ftw/faqblock/profiles/default/types.xml
ftw/faqblock/profiles/default/workflows.xml
ftw/faqblock/profiles/default-plone5/browserlayer.xml
ftw/faqblock/profiles/default-plone5/metadata.xml
ftw/faqblock/profiles/default-plone5/registry.xml
ftw/faqblock/profiles/default-plone5/rolemap.xml
ftw/faqblock/profiles/default-plone5/types.xml
ftw/faqblock/profiles/default-plone5/workflows.xml
ftw/faqblock/profiles/default-plone5/types/Plone_Site.xml
ftw/faqblock/profiles/default-plone5/types/ftw.faqblock.FaqBlock.xml
ftw/faqblock/profiles/default-plone5/types/ftw.simplelayout.ContentPage.xml
ftw/faqblock/profiles/default/types/Plone_Site.xml
ftw/faqblock/profiles/default/types/ftw.faqblock.FaqBlock.xml
ftw/faqblock/profiles/default/types/ftw.simplelayout.ContentPage.xml
ftw/faqblock/profiles/uninstall/browserlayer.xml
ftw/faqblock/profiles/uninstall/jsregistry.xml
ftw/faqblock/profiles/uninstall/propertiestool.xml
ftw/faqblock/profiles/uninstall/rolemap.xml
